funccache/__init__.py
funccache/i funccache.py
funccache-2.0.4.dist-info/LICENSE
funccache-2.0.4.dist-info/METADATA
funccache-2.0.4.dist-info/WHEEL
funccache-2.0.4.dist-info/top_level.txt
funccache-2.0.4.dist-info/RECORD
