Metadata-Version: 2.1
Name: funccache
Version: 2.0.4
Summary: True to its name, `funccache` implements the cache function. Cache the return value of a callable object or all methods defined in a class.
Home-page: http://gqylpy.com
Author: 竹永康
Author-email: <gqylpy@outlook.com>
License: Apache 2.0
Project-URL: Source, https://github.com/gqylpy/funccache
Classifier: Development Status :: 4 - Beta
Classifier: Intended Audience :: Developers
Classifier: License :: OSI Approved :: Apache Software License
Classifier: Natural Language :: Chinese (Simplified)
Classifier: Natural Language :: English
Classifier: Operating System :: OS Independent
Classifier: Topic :: Artistic Software
Classifier: Topic :: Software Development :: Libraries :: Python Modules
Classifier: Programming Language :: Python :: 3.8
Classifier: Programming Language :: Python :: 3.9
Classifier: Programming Language :: Python :: 3.10
Classifier: Programming Language :: Python :: 3.11
Classifier: Programming Language :: Python :: 3.12
Classifier: Programming Language :: Python :: 3.13
Requires-Python: >=3.8
License-File: LICENSE
